{
  "strategy_name": "AlphaStrategy",
  "params": {
    "max_open_trades": {
      "max_open_trades": 9
    },
    "buy": {
      "buy_rsi": 39,
      "leverage_num": 3
    },
    "sell": {
      "sell_rsi": 60
    },
    "roi": {
      "0": 0.162,
      "40": 0.052,
      "68": 0.039,
      "179": 0
    },
    "stoploss": {
      "stoploss": -0.287
    },
    "trailing": {
      "trailing_stop": true,
      "trailing_stop_positive": 0.045,
      "trailing_stop_positive_offset": 0.097,
      "trailing_only_offset_is_reached": true
    }
  },
  "ft_stratparam_v": 1,
  "export_time": "2026-03-04 15:48:12.662885+00:00"
}